mseep_biggo_mcp_server-1.0.1.dist-info/licenses/LICENSE
test/__init__.py
test/helper.py
test/test_api_ret.py
test/test_responses.py
test/test_services.py
test/test_setting.py
test/test_tools.py
mseep_biggo_mcp_server-1.0.1.dist-info/METADATA
mseep_biggo_mcp_server-1.0.1.dist-info/WHEEL
mseep_biggo_mcp_server-1.0.1.dist-info/top_level.txt
mseep_biggo_mcp_server-1.0.1.dist-info/RECORD
